<?xml version="1.0" encoding="utf-8"?>
<!-- Created by ModBuddy on 3/2/2014 9:58:33 AM -->
<GameData>
	<IconTextureAtlases>
		<Row>
			<Atlas>MEC_ICON_ATLAS</Atlas>
			<IconSize>256</IconSize>
			<Filename>MECIconAtlas256.dds</Filename>
			<IconsPerRow>8</IconsPerRow>
			<IconsPerColumn>8</IconsPerColumn>
		</Row>
		<Row>
			<Atlas>MEC_ICON_ATLAS</Atlas>
			<IconSize>128</IconSize>
			<Filename>MECIconAtlas128.dds</Filename>
			<IconsPerRow>8</IconsPerRow>
			<IconsPerColumn>8</IconsPerColumn>
		</Row>
		<Row>
			<Atlas>MEC_ICON_ATLAS</Atlas>
			<IconSize>80</IconSize>
			<Filename>MECIconAtlas80.dds</Filename>
			<IconsPerRow>8</IconsPerRow>
			<IconsPerColumn>8</IconsPerColumn>
		</Row>
		<Row>
			<Atlas>MEC_ICON_ATLAS</Atlas>
			<IconSize>64</IconSize>
			<Filename>MECIconAtlas64.dds</Filename>
			<IconsPerRow>8</IconsPerRow>
			<IconsPerColumn>8</IconsPerColumn>
		</Row>
		<Row>
			<Atlas>MEC_ICON_ATLAS</Atlas>
			<IconSize>45</IconSize>
			<Filename>MECIconAtlas45.dds</Filename>
			<IconsPerRow>8</IconsPerRow>
			<IconsPerColumn>8</IconsPerColumn>
		</Row>
		<Row>
			<Atlas>MEC_ICON_ATLAS</Atlas>
			<IconSize>32</IconSize>
			<Filename>MECIconAtlas32.dds</Filename>
			<IconsPerRow>8</IconsPerRow>
			<IconsPerColumn>8</IconsPerColumn>
		</Row>
		<Row>
			<Atlas>MEC_ICON_ATLAS_ALPHA</Atlas>
			<IconSize>256</IconSize>
			<Filename>MECIconAtlasAlpha256.dds</Filename>
			<IconsPerRow>8</IconsPerRow>
			<IconsPerColumn>8</IconsPerColumn>
		</Row>
		<Row>
			<Atlas>MEC_ICON_ATLAS_ALPHA</Atlas>
			<IconSize>128</IconSize>
			<Filename>MECIconAtlasAlpha128.dds</Filename>
			<IconsPerRow>8</IconsPerRow>
			<IconsPerColumn>8</IconsPerColumn>
		</Row>
		
		<Row>
			<Atlas>MEC_ICON_ATLAS_ALPHA</Atlas>
			<IconSize>24</IconSize>
			<Filename>MECIconAtlasAlpha24.dds</Filename>
			<IconsPerRow>8</IconsPerRow>
			<IconsPerColumn>8</IconsPerColumn>
		</Row>
		
		
		<Row>
			<Atlas>MEC_ICON_ATLAS_ALPHA</Atlas>
			<IconSize>214</IconSize>
			<Filename>MECIconAtlasAlpha214.dds</Filename>
			<IconsPerRow>8</IconsPerRow>
			<IconsPerColumn>8</IconsPerColumn>
		</Row>	
		<Row>
			<Atlas>MEC_ICON_ATLAS_ALPHA</Atlas>
			<IconSize>16</IconSize>
			<Filename>MECIconAtlasAlpha16.dds</Filename>
			<IconsPerRow>8</IconsPerRow>
			<IconsPerColumn>8</IconsPerColumn>
		</Row>
		<Row>
			<Atlas>MEC_ICON_ATLAS_ALPHA</Atlas>
			<IconSize>48</IconSize>
			<Filename>MECIconAtlasAlpha48.dds</Filename>
			<IconsPerRow>8</IconsPerRow>
			<IconsPerColumn>8</IconsPerColumn>
		</Row>
		
		<Row>
			<Atlas>MEC_ICON_ATLAS_ALPHA</Atlas>
			<IconSize>80</IconSize>
			<Filename>MECIconAtlasAlpha80.dds</Filename>
			<IconsPerRow>8</IconsPerRow>
			<IconsPerColumn>8</IconsPerColumn>
		</Row>
		<Row>
			<Atlas>MEC_ICON_ATLAS_ALPHA</Atlas>
			<IconSize>64</IconSize>
			<Filename>MECIconAtlasAlpha64.dds</Filename>
			<IconsPerRow>8</IconsPerRow>
			<IconsPerColumn>8</IconsPerColumn>
		</Row>
		
		<Row>
			<Atlas>MEC_ICON_ATLAS_ALPHA</Atlas>
			<IconSize>45</IconSize>
			<Filename>MECIconAtlasAlpha45.dds</Filename>
			<IconsPerRow>8</IconsPerRow>
			<IconsPerColumn>8</IconsPerColumn>
		</Row>
		<Row>
			<Atlas>MEC_ICON_ATLAS_ALPHA</Atlas>
			<IconSize>32</IconSize>
			<Filename>MECIconAtlasAlpha32.dds</Filename>
			<IconsPerRow>8</IconsPerRow>
			<IconsPerColumn>8</IconsPerColumn>
		</Row>
	
		<Row>
			<Atlas>MEC_UNIT_FLAG_ATLAS</Atlas>
			<IconSize>32</IconSize>
			<Filename>MECUnitFlagAtlas32.dds</Filename>
			<IconsPerRow>8</IconsPerRow>
			<IconsPerColumn>8</IconsPerColumn>
		</Row>
	</IconTextureAtlases>
</GameData>